linovelib/__init__.py
linovelib/__main__.py
linovelib/linovelib_all.py
linovelib/linovelib_download.py
linovelib-0.0.4.dist-info/LICENSE
linovelib-0.0.4.dist-info/METADATA
linovelib-0.0.4.dist-info/WHEEL
linovelib-0.0.4.dist-info/entry_points.txt
linovelib-0.0.4.dist-info/top_level.txt
linovelib-0.0.4.dist-info/zip-safe
linovelib-0.0.4.dist-info/RECORD
