Metadata-Version: 2.1
Name: linovelib
Version: 0.0.4
Summary: Download novel from linovelib
Home-page: https://gitee.com/lensit/linovelib
Author: Lensit
Author-email: 1570515219@qq.com
License: MIT License
Platform: UNKNOWN
License-File: LICENSE
Requires-Dist: bs4
Requires-Dist: fire
Requires-Dist: requests
Requires-Dist: fake-useragent
Requires-Dist: pypandoc
